README.md
setup.py
ipywidgets_server/__init__.py
ipywidgets_server/_version.py
ipywidgets_server/app.py
ipywidgets_server/kernel.json
ipywidgets_server/test.py
ipywidgets_server.egg-info/PKG-INFO
ipywidgets_server.egg-info/SOURCES.txt
ipywidgets_server.egg-info/dependency_links.txt
ipywidgets_server.egg-info/entry_points.txt
ipywidgets_server.egg-info/not-zip-safe
ipywidgets_server.egg-info/requires.txt
ipywidgets_server.egg-info/top_level.txt
ipywidgets_server/kernel/__init__.py
ipywidgets_server/kernel/__main__.py
ipywidgets_server/static/index.html
ipywidgets_server/static/main.js
ipywidgets_server/static/dist/0.libwidgets.js
ipywidgets_server/static/dist/0.libwidgets.js.map
ipywidgets_server/static/dist/674f50d287a8c48dc19ba404d20fe713.eot
ipywidgets_server/static/dist/912ec66d7572ff821749319396470bde.svg
ipywidgets_server/static/dist/af7ae505a9eed503f8b8e6982036873e.woff2
ipywidgets_server/static/dist/b06871f281fee6b241d60582ae9369b9.ttf
ipywidgets_server/static/dist/fee66e712a8a08eef5805a46892932ad.woff
ipywidgets_server/static/dist/libwidgets.js
ipywidgets_server/static/dist/libwidgets.js.map
ipywidgets_server/static/dist/@jupyter-widgets/base.js
ipywidgets_server/static/dist/@jupyter-widgets/controls.js