Metadata-Version: 1.0
Name: ipywidgets-server
Version: 0.1.3
Summary: Standalone server for ipywidgets
Home-page: UNKNOWN
Author: Pascal Bugnion
Author-email: pascal@bugnion.org
License: UNKNOWN
Keywords: ipython,jupyter,widgets
Platform: UNKNOWN
